{
   "result" : {
      "str_join_repeat" : {
         "perl" : 2,
         "perl6" : 21,
         "nim" : 66,
         "lua" : 76,
         "ruby" : 56
      },
      "re_capture" : {
         "lua" : 252,
         "ruby" : 401,
         "javascript" : 94,
         "perl6" : 15240,
         "perl" : 159
      },
      "re_bool" : {
         "perl" : 431,
         "perl6" : 3328,
         "javascript" : 48,
         "ruby" : 126,
         "lua" : 175
      },
      "str_join_slow" : {
         "perl6" : 6032,
         "c#" : 196,
         "javascript" : 277,
         "ruby" : 15739,
         "lua" : 9318,
         "perl" : 1326,
         "c++" : 60,
         "nim" : 362
      },
      "str_join" : {
         "nim" : 48,
         "c++" : 3,
         "perl" : 416,
         "lua" : 205,
         "ruby" : 1223,
         "c#" : 169,
         "javascript" : 46,
         "perl6" : 2200
      },
      "json_se" : {
         "javascript" : 603,
         "ruby" : 3814,
         "perl" : 363
      },
      "json_de" : {
         "javascript" : 770,
         "ruby" : 2530,
         "perl" : 762
      },
      "takeuchi" : {
         "perl6" : 26962,
         "javascript" : 317,
         "c#" : 256,
         "ruby" : 1885,
         "lua" : 348,
         "perl" : 11474,
         "c++" : 18,
         "nim" : 138
      },
      "fib_fast" : {
         "perl6" : 2969,
         "javascript" : 18
      },
      "fib" : {
         "lua" : 135,
         "c#" : 59,
         "javascript" : 115,
         "ruby" : 792,
         "perl6" : 13650,
         "nim" : 31,
         "c++" : 4,
         "perl" : 4605
      }
   },
   "version" : {
      "lua" : "2.0.5",
      "c#" : "2.2.108",
      "javascript" : "v13.5.0",
      "ruby" : "2.6.5p114",
      "perl6" : "2019.11",
      "nim" : "1.0.4",
      "c++" : "9.0.1",
      "perl" : "v5.30.1"
   }
}
