{
   "result" : {
      "fib" : {
         "perl6" : 13851,
         "c#" : 58,
         "javascript" : 106,
         "perl" : 4805,
         "nim" : 33,
         "c++" : 4,
         "ruby" : 774,
         "lua" : 132
      },
      "re_capture" : {
         "lua" : 250,
         "perl" : 159,
         "javascript" : 70,
         "ruby" : 408,
         "perl6" : 21041
      },
      "json_de" : {
         "ruby" : 3456,
         "perl" : 852,
         "javascript" : 754
      },
      "takeuchi" : {
         "c#" : 260,
         "perl6" : 26462,
         "lua" : 350,
         "c++" : 36,
         "ruby" : 1853,
         "javascript" : 236,
         "nim" : 100,
         "perl" : 12222
      },
      "json_se" : {
         "javascript" : 554,
         "perl" : 394,
         "ruby" : 3079
      },
      "fib_fast" : {
         "javascript" : 17,
         "perl6" : 3894
      },
      "str_join_repeat" : {
         "lua" : 76,
         "ruby" : 59,
         "perl6" : 8,
         "nim" : 54,
         "perl" : 2
      },
      "re_bool" : {
         "lua" : 172,
         "perl" : 438,
         "javascript" : 36,
         "perl6" : 5378,
         "ruby" : 122
      },
      "str_join_slow" : {
         "lua" : 9525,
         "javascript" : 201,
         "perl" : 1374,
         "nim" : 462,
         "c++" : 50,
         "ruby" : 18772,
         "c#" : 234,
         "perl6" : 9710
      },
      "str_join" : {
         "c++" : 4,
         "ruby" : 1246,
         "javascript" : 46,
         "nim" : 46,
         "perl" : 425,
         "lua" : 210,
         "perl6" : 2399,
         "c#" : 196
      }
   },
   "version" : {
      "c#" : "2.2.108",
      "perl6" : "2019.03.1",
      "lua" : "2.0.5",
      "javascript" : "v12.13.0",
      "nim" : "0.18.0",
      "perl" : "v5.30.0",
      "c++" : "9.0.0",
      "ruby" : "2.6.5p114"
   }
}
