{
   "version" : {
      "lua" : "2.1.0",
      "nim" : "1.6.10",
      "javascript" : "v20.2.0",
      "c#" : "7.0.103",
      "ruby" : "3.0.5p211",
      "c++" : "15.0.7",
      "nqp" : "2023.04-1-gdb7d603cd",
      "perl6" : null,
      "perl" : "v5.36.1"
   },
   "result" : {
      "re_bool" : {
         "nqp" : 0,
         "perl6" : 2514,
         "perl" : 447,
         "ruby" : 160,
         "lua" : 193,
         "javascript" : 34
      },
      "json_se" : {
         "javascript" : 638,
         "perl" : 358,
         "ruby" : 1964
      },
      "fib_fast" : {
         "javascript" : 17,
         "perl6" : 2490
      },
      "str_join_repeat" : {
         "ruby" : 52,
         "perl" : 3,
         "nim" : 49,
         "lua" : 1,
         "perl6" : 5
      },
      "takeuchi" : {
         "javascript" : 300,
         "nim" : 47,
         "lua" : 423,
         "c++" : 17,
         "ruby" : 2187,
         "c#" : 0,
         "perl" : 11888,
         "perl6" : 12321,
         "nqp" : 0
      },
      "str_join" : {
         "lua" : 91,
         "nim" : 49,
         "javascript" : 48,
         "c#" : 0,
         "c++" : 0,
         "ruby" : 1449,
         "nqp" : 0,
         "perl6" : 2168,
         "perl" : 437
      },
      "re_capture" : {
         "javascript" : 75,
         "lua" : 281,
         "perl" : 160,
         "nqp" : 0,
         "perl6" : 11417,
         "ruby" : 484
      },
      "str_join_slow" : {
         "c++" : 61,
         "ruby" : 13953,
         "c#" : 0,
         "perl" : 1362,
         "perl6" : 6563,
         "nim" : 369,
         "javascript" : 154,
         "lua" : 8081
      },
      "json_de" : {
         "javascript" : 739,
         "perl" : 750,
         "ruby" : 2021
      },
      "fib" : {
         "c#" : 0,
         "c++" : 2,
         "ruby" : 859,
         "perl6" : 4992,
         "nqp" : 0,
         "perl" : 4866,
         "lua" : 216,
         "nim" : 15,
         "javascript" : 137
      }
   }
}
