{
   "result" : {
      "fib" : {
         "ruby" : 821,
         "lua" : 201,
         "perl6" : 4998,
         "c++" : 2,
         "nqp" : 0,
         "perl" : 4635,
         "nim" : 15,
         "c#" : 0,
         "javascript" : 124
      },
      "takeuchi" : {
         "lua" : 416,
         "ruby" : 2109,
         "perl6" : 12053,
         "c++" : 17,
         "nqp" : 0,
         "perl" : 11172,
         "nim" : 46,
         "javascript" : 256,
         "c#" : 0
      },
      "re_capture" : {
         "lua" : 246,
         "perl" : 158,
         "ruby" : 443,
         "perl6" : 10793,
         "nqp" : 0,
         "javascript" : 80
      },
      "str_join" : {
         "perl6" : 1948,
         "lua" : 93,
         "ruby" : 1340,
         "nqp" : 0,
         "c++" : 0,
         "nim" : 50,
         "perl" : 415,
         "javascript" : 44,
         "c#" : 0
      },
      "json_se" : {
         "ruby" : 1874,
         "perl" : 343,
         "javascript" : 609
      },
      "str_join_repeat" : {
         "nim" : 55,
         "perl6" : 5,
         "perl" : 3,
         "ruby" : 50,
         "lua" : 1
      },
      "re_bool" : {
         "ruby" : 153,
         "perl" : 423,
         "lua" : 164,
         "perl6" : 2392,
         "nqp" : 0,
         "javascript" : 35
      },
      "fib_fast" : {
         "javascript" : 15,
         "perl6" : 2148
      },
      "json_de" : {
         "javascript" : 728,
         "perl" : 688,
         "ruby" : 1879
      },
      "str_join_slow" : {
         "c++" : 56,
         "perl6" : 6430,
         "lua" : 7468,
         "ruby" : 12355,
         "javascript" : 200,
         "c#" : 0,
         "nim" : 355,
         "perl" : 1280
      }
   },
   "version" : {
      "ruby" : "3.0.5p211",
      "lua" : "2.1.0",
      "perl6" : null,
      "c++" : "15.0.7",
      "nqp" : "2023.02-4-g90ca9a6e8",
      "perl" : "v5.36.0",
      "nim" : "1.6.10",
      "c#" : "7.0.103",
      "javascript" : "v19.8.1"
   }
}
